maro/__misc__.py
maro/__init__.py
maro/common.py
maro/simulator/__init__.py
maro/simulator/core.py
maro/simulator/abs_core.py
maro/simulator/scenarios/__init__.py
maro/simulator/scenarios/matrix_accessor.py
maro/simulator/scenarios/abs_business_engine.py
maro/simulator/scenarios/helpers.py
maro/simulator/scenarios/vm_scheduling/zone.py
maro/simulator/scenarios/vm_scheduling/data_center.py
maro/simulator/scenarios/vm_scheduling/physical_machine.py
maro/simulator/scenarios/vm_scheduling/region.py
maro/simulator/scenarios/vm_scheduling/__init__.py
maro/simulator/scenarios/vm_scheduling/business_engine.py
maro/simulator/scenarios/vm_scheduling/frame_builder.py
maro/simulator/scenarios/vm_scheduling/virtual_machine.py
maro/simulator/scenarios/vm_scheduling/rack.py
maro/simulator/scenarios/vm_scheduling/enums.py
maro/simulator/scenarios/vm_scheduling/cpu_reader.py
maro/simulator/scenarios/vm_scheduling/cluster.py
maro/simulator/scenarios/vm_scheduling/common.py
maro/simulator/scenarios/vm_scheduling/meta/source_urls.yml
maro/simulator/scenarios/vm_scheduling/meta/vmtable.yml
maro/simulator/scenarios/vm_scheduling/meta/cpu_readings.yml
maro/simulator/scenarios/vm_scheduling/topologies/azure.2019.10k/config.yml
maro/simulator/scenarios/vm_scheduling/topologies/azure.2019.336k.oversubscription/config.yml
maro/simulator/scenarios/vm_scheduling/topologies/azure.2019.336k.oversubscription.multi_clusters/config.yml
maro/simulator/scenarios/vm_scheduling/topologies/azure.2019.336k/config.yml
maro/simulator/scenarios/vm_scheduling/topologies/azure.2019.10k.oversubscription/config.yml
maro/simulator/scenarios/cim/event_payload.py
maro/simulator/scenarios/cim/vessel.py
maro/simulator/scenarios/cim/__init__.py
maro/simulator/scenarios/cim/business_engine.py
maro/simulator/scenarios/cim/events.py
maro/simulator/scenarios/cim/frame_builder.py
maro/simulator/scenarios/cim/matrix.py
maro/simulator/scenarios/cim/port.py
pymaro-0.3.2a4.dist-info/entry_points.txt
pymaro-0.3.2a4.dist-info/LICENSE
pymaro-0.3.2a4.dist-info/WHEEL
pymaro-0.3.2a4.dist-info/METADATA
pymaro-0.3.2a4.dist-info/RECORD
pymaro-0.3.2a4.dist-info/top_level.txt
