Metadata-Version: 2.1
Name: pymaro
Version: 0.3.2a4
Summary: MARO Python Package
Home-page: https://github.com/microsoft/maro
Author: MARO Team
Author-email: maro-team@microsoft.com
License: MIT License
Project-URL: Code, https://github.com/microsoft/maro
Project-URL: Issues, https://github.com/microsoft/maro/issues
Project-URL: Documents, https://maro.readthedocs.io/en/latest
Keywords: citi-bike,inventory-management,operations-research,reinforcement-learning,resource-optimization,simulator
Platform: Windows
Platform: Linux
Platform: macOS
Classifier: Intended Audience :: Science/Research
Classifier: License :: OSI Approved :: MIT License
Classifier: Natural Language :: English
Classifier: Operating System :: MacOS
Classifier: Operating System :: Microsoft :: Windows
Classifier: Operating System :: POSIX
Classifier: Operating System :: Unix
Classifier: Programming Language :: Python
Classifier: Programming Language :: Python :: 3
Classifier: Programming Language :: Python :: 3.7
Classifier: Programming Language :: Python :: 3.8
Classifier: Programming Language :: Python :: 3.9
Classifier: Topic :: Scientific/Engineering :: Artificial Intelligence
Requires-Python: >=3.7
License-File: LICENSE
